hiMoon/__init__.py
hiMoon/__main__.py
hiMoon/config.py
hiMoon/gene.py
hiMoon/haplotype.py
hiMoon/himoon.py
hiMoon/subject.py
hiMoon/vcf.py
hiMoon/template/__init__.py
hiMoon/template/template.vcf
hiMoon/tests/__init__.py
hiMoon/tests/haplotype_test.py
hiMoon/tests/hiMoon_test.py
hiMoon-0.13.7.dist-info/LICENSE
hiMoon-0.13.7.dist-info/METADATA
hiMoon-0.13.7.dist-info/WHEEL
hiMoon-0.13.7.dist-info/entry_points.txt
hiMoon-0.13.7.dist-info/top_level.txt
hiMoon-0.13.7.dist-info/RECORD
