Metadata-Version: 2.1
Name: hiMoon
Version: 0.13.7
Summary: Define names haplotypes from data stored in VCF
Home-page: UNKNOWN
Author: Solomon M. Adams, PharmD, PhD
Author-email: sadams2013@gmail.com
License: UNKNOWN
Platform: UNKNOWN
Classifier: Programming Language :: Python :: 3.6
Classifier: Programming Language :: Python :: 3.7
Classifier: Programming Language :: Python :: 3.8
Classifier: Programming Language :: Python :: 3.9
Classifier: Development Status :: 4 - Beta
Classifier: Environment :: Console
Classifier: License :: OSI Approved :: Apache Software License
Classifier: Operating System :: POSIX
Classifier: Intended Audience :: Science/Research
Classifier: Intended Audience :: Healthcare Industry
License-File: LICENSE
Requires-Dist: pulp
Requires-Dist: pandas
Requires-Dist: pysam
Requires-Dist: numpy
